cherrypy_misfortune/__init__.py
cherrypy_misfortune-1.0.dist-info/DESCRIPTION.rst
cherrypy_misfortune-1.0.dist-info/METADATA
cherrypy_misfortune-1.0.dist-info/RECORD
cherrypy_misfortune-1.0.dist-info/WHEEL
cherrypy_misfortune-1.0.dist-info/metadata.json
cherrypy_misfortune-1.0.dist-info/top_level.txt
