Metadata-Version: 2.0
Name: cherrypy-misfortune
Version: 1.0
Summary: CherryPy tool that causes requests to stall or fail with the aim of assisting the development of robust consumers
Home-page: https://bitbucket.org/gclinch/cherrypy-misfortune
Author: Graham Clinch
Author-email: g.clinch@lancaster.ac.uk
License: Apache License, Version 2.0
Platform: UNKNOWN
Classifier: Development Status :: 5 - Production/Stable
Classifier: Framework :: CherryPy
Classifier: Intended Audience :: Developers
Classifier: License :: OSI Approved :: Apache Software License
Requires-Dist: CherryPy
